{
  "$schema": "https://schemas.tauri.app/capability/2",
  "identifier": "default",
  "description": "Default permissions for terX",
  "windows": ["main", "debug"],
  "permissions": [
    "core:default",
    "core:event:default",
    "core:event:allow-emit",
    "core:event:allow-listen",
    "core:window:default",
    "core:window:allow-create",
    "core:window:allow-close",
    "core:window:allow-set-focus",
    "core:webview:default",
    "core:webview:allow-create-webview-window",
    "opener:default",
    "deep-link:default"
  ]
}
